meross_device/__init__.py
meross_device/fhem_device.py
meross_device/garage_door_opener.py
meross_device/meross.py
meross_device/meross_daemon.py
meross_device/meross_device.py
meross_device/meross_fhem_device.py
meross_device/plug.py
MEROSS_DEVICE_DeGriesche-0.0.2.dist-info/LICENSE
MEROSS_DEVICE_DeGriesche-0.0.2.dist-info/METADATA
MEROSS_DEVICE_DeGriesche-0.0.2.dist-info/WHEEL
MEROSS_DEVICE_DeGriesche-0.0.2.dist-info/top_level.txt
MEROSS_DEVICE_DeGriesche-0.0.2.dist-info/RECORD
