Metadata-Version: 2.1
Name: MEROSS-DEVICE-DeGriesche
Version: 0.0.2
Summary: Meross Python integration for FHEM module MEROSS_DEVICE
Home-page: https://github.com/DeGriesche/MEROSS_DEVICE
Author: Manolis Pavlakis
Author-email: m.pavlakis@hotmail.de
License: UNKNOWN
Project-URL: Bug Tracker, https://github.com/DeGriesche/MEROSS_DEVICE/issues
Platform: UNKNOWN
Classifier: Programming Language :: Python :: 3
Classifier: License :: OSI Approved :: MIT License
Classifier: Operating System :: OS Independent
Requires-Python: >=3.6
License-File: LICENSE
